LICENSE
MANIFEST.in
README.rst
setup.cfg
setup.py
./__init__.py
./carrier.py
./carrier.xml
./carrier_box_type.xml
./country.py
./country.xml
./party.py
./sale.py
./sale.xml
./shipment_bag.py
./shipping_data.xml
./stock.py
./stock.xml
./tryton.cfg
./tests/__init__.py
./tests/test_carrier.py
./tests/test_endicia.py
./tests/test_stock.py
./view/carrier_form.xml
./view/endicia_buy_postage_wizard_view_form.xml
./view/endicia_refund_wizard_view_form.xml
./view/endicia_scanform_wizard_view_form.xml
./view/mailclass_view_form.xml
./view/mailclass_view_tree.xml
./view/sale_configuration_view_form.xml
./view/shipment_view_form.xml
./view/shipping_endicia_configuration_form.xml
fio_shipping_endicia.egg-info/PKG-INFO
fio_shipping_endicia.egg-info/SOURCES.txt
fio_shipping_endicia.egg-info/dependency_links.txt
fio_shipping_endicia.egg-info/entry_points.txt
fio_shipping_endicia.egg-info/not-zip-safe
fio_shipping_endicia.egg-info/requires.txt
fio_shipping_endicia.egg-info/top_level.txt